nyt_most_popular/__init__.py
nyt_most_popular/sdk.py
nyt_most_popular/hooks/__init__.py
nyt_most_popular/hooks/hook.py
nyt_most_popular/models/__init__.py
nyt_most_popular/models/base.py
nyt_most_popular/models/emailed_article.py
nyt_most_popular/models/get_emailed_period_json_ok_response.py
nyt_most_popular/models/get_emailed_period_json_period.py
nyt_most_popular/models/get_shared_by_period_share_type_json_ok_response.py
nyt_most_popular/models/get_shared_by_period_share_type_json_period.py
nyt_most_popular/models/get_shared_period_json_ok_response.py
nyt_most_popular/models/get_shared_period_json_period.py
nyt_most_popular/models/get_viewed_period_json_ok_response.py
nyt_most_popular/models/get_viewed_period_json_period.py
nyt_most_popular/models/media.py
nyt_most_popular/models/media_metadata.py
nyt_most_popular/models/share_type.py
nyt_most_popular/models/shared_article.py
nyt_most_popular/models/viewed_article.py
nyt_most_popular/models/utils/cast_models.py
nyt_most_popular/models/utils/json_map.py
nyt_most_popular/net/__init__.py
nyt_most_popular/net/environment/__init__.py
nyt_most_popular/net/environment/environment.py
nyt_most_popular/net/headers/__init__.py
nyt_most_popular/net/headers/base_header.py
nyt_most_popular/net/request_chain/__init__.py
nyt_most_popular/net/request_chain/request_chain.py
nyt_most_popular/net/request_chain/handlers/__init__.py
nyt_most_popular/net/request_chain/handlers/base_handler.py
nyt_most_popular/net/request_chain/handlers/hook_handler.py
nyt_most_popular/net/request_chain/handlers/http_handler.py
nyt_most_popular/net/request_chain/handlers/retry_handler.py
nyt_most_popular/net/transport/__init__.py
nyt_most_popular/net/transport/request.py
nyt_most_popular/net/transport/request_error.py
nyt_most_popular/net/transport/response.py
nyt_most_popular/net/transport/serializer.py
nyt_most_popular/net/transport/utils.py
nyt_most_popular/services/__init__.py
nyt_most_popular/services/most_popular.py
nyt_most_popular-1.0.0.dist-info/LICENSE
nyt_most_popular-1.0.0.dist-info/METADATA
nyt_most_popular-1.0.0.dist-info/WHEEL
nyt_most_popular-1.0.0.dist-info/top_level.txt
nyt_most_popular-1.0.0.dist-info/RECORD
