Metadata-Version: 2.1
Name: nyt-most-popular
Version: 1.0.0
Summary: Provides services for getting the most popular articles on NYTimes.com based on emails, shares, or views.
License: MIT
Requires-Python: >=3.7
License-File: LICENSE
Requires-Dist: requests >=2.31.0
